Metadata-Version: 2.1
Name: xdclient
Version: 0.1.4
Summary: X-Developer Command Line Client
Home-page: https://x-developer.cn
Author: Chen Jiaxing
Author-email: jxchen@withfield.tech
License: MIT
Keywords: X-Developer,git,client,git log analysis
Platform: UNKNOWN
Classifier: Intended Audience :: Developers
Classifier: License :: OSI Approved :: MIT License
Classifier: Natural Language :: English
Classifier: Programming Language :: Python :: 3.4
Classifier: Programming Language :: Python :: 3.5
Classifier: Programming Language :: Python :: 3.6
Requires-Python: >=2.7.6
